{
  "en": {
    "translation": {
      "MainPage": "Main Page",
      "SiteDescription": "This is a portal about Belarussian architects. It is made by Awesome Random Party.",
      "Dzmitry Tsebruk": "Dzmitry Tsebruk",
      "Aleh Serhiyenia": "Aleh Serhiyenia",
      "Dzianis Hancharou": "Dzianis Hancharou",
      "Volha Naranovich": "Volha Naranovich",
      "Kiryl Horbikau": "Kiryl Horbikau"
    }
  },
  "ru": {
    "translation": {
      "MainPage": "Главная страница",
      "SiteDescription": "Это портал о белорусских архитекторах. Он был сделан командой Awesome Random Party.",
      "Dzmitry Tsebruk": "Дмитрий Цебрук",
      "Aleh Serhiyenia": "Олег Сергиеня",
      "Dzianis Hancharou": "Денис Гончаров",
      "Volha Naranovich": "Ольга Наранович",
      "Kiryl Horbikau": "Кирилл Горбиков"
    }
  },
  "by": {
    "translation": {
      "MainPage": "Галоуная старонка",
      "SiteDescription": "Гэта партал пра беларускіх архітэктараў. Ён быў зроблены камандай Awesome Random Party.",
      "Dzmitry Tsebruk": "Дзмітрый Цэбрук",
      "Aleh Serhiyenia": "Алег Сергіеня",
      "Dzianis Hancharou": "Дзяніс Ганчароў",
      "Volha Naranovich": "Вольга Нарановіч",
      "Kiryl Horbikau": "Кірыл Горбікаў"
    }
  }
}